README.md
setup.py
PyMMonit.egg-info/PKG-INFO
PyMMonit.egg-info/SOURCES.txt
PyMMonit.egg-info/dependency_links.txt
PyMMonit.egg-info/requires.txt
PyMMonit.egg-info/top_level.txt
pymmonit/__init__.py
pymmonit/_version.py
pymmonit/mmonit.py
pymmonit.egg-info/PKG-INFO
pymmonit.egg-info/SOURCES.txt
pymmonit.egg-info/dependency_links.txt
pymmonit.egg-info/requires.txt
pymmonit.egg-info/top_level.txt