Metadata-Version: 1.0
Name: pymmonit
Version: 0.5.0
Summary: MMonit API wrapper written in Python
Home-page: https://github.com/jthacker/PyMMonit
Author: Jon Thacker
Author-email: thacker.jon@gmail.com
License: GPLv3
Platform: UNKNOWN
